Metadata-Version: 2.4
Name: pybiber
Version: 0.3.0
Summary: Extract Biber features from a document parsed and annotated by spaCy.
Author-email: David Brown <dwb2@andrew.cmu.edu>
Maintainer-email: David Brown <dwb2@andrew.cmu.edu>
License: MIT License
Project-URL: Homepage, https://github.com/browndw/pybiber
Project-URL: Documentation, https://browndw.github.io/pybiber
Keywords: nlp,language
Classifier: Programming Language :: Python :: 3 :: Only
Classifier: Programming Language :: Python :: 3.10
Classifier: Programming Language :: Python :: 3.11
Classifier: Programming Language :: Python :: 3.12
Classifier: License :: OSI Approved :: MIT License
Requires-Python: >=3.10
License-File: LICENSE
Requires-Dist: adjustText>=1.1
Requires-Dist: polars>=1.17
Requires-Dist: spacy>=3.7
Provides-Extra: test
Requires-Dist: pytest; extra == "test"
Requires-Dist: pytest-cov; extra == "test"
Requires-Dist: factor-analyzer>=0.5.1; extra == "test"
Requires-Dist: scikit-learn<1.4; extra == "test"
Provides-Extra: spacy-model
Requires-Dist: en_core_web_sm>=3.7.0; extra == "spacy-model"
Dynamic: license-file
